{
  "slides": [
    {
      "loop": false,
      "auto_next": false,
      "playback_rate": 1.0,
      "reversed_playback_rate": 1.0,
      "notes": "",
      "dedent_notes": true,
      "skip_animations": false,
      "src": null,
      "type": "video",
      "direction": "horizontal",
      "file": "slides\\files\\LeastSq\\85903ee9eb4c0331572725963289a7b604023f400f342f500d7214684d0e67d1.mp4",
      "rev_file": "slides\\files\\LeastSq\\85903ee9eb4c0331572725963289a7b604023f400f342f500d7214684d0e67d1_reversed.mp4"
    },
    {
      "loop": false,
      "auto_next": false,
      "playback_rate": 1.0,
      "reversed_playback_rate": 1.0,
      "notes": "",
      "dedent_notes": true,
      "skip_animations": false,
      "src": null,
      "type": "video",
      "direction": "horizontal",
      "file": "slides\\files\\LeastSq\\c752b5dab5d53c4bc7780c1cffa01616b477606864a19d267048c14ac6e70752.mp4",
      "rev_file": "slides\\files\\LeastSq\\c752b5dab5d53c4bc7780c1cffa01616b477606864a19d267048c14ac6e70752_reversed.mp4"
    },
    {
      "loop": false,
      "auto_next": false,
      "playback_rate": 1.0,
      "reversed_playback_rate": 1.0,
      "notes": "",
      "dedent_notes": true,
      "skip_animations": false,
      "src": null,
      "type": "video",
      "direction": "horizontal",
      "file": "slides\\files\\LeastSq\\6dcc49b0a5c27305414f4e0b0b1de35978af24cfe0167cb8c7dddadeecea5bf4.mp4",
      "rev_file": "slides\\files\\LeastSq\\6dcc49b0a5c27305414f4e0b0b1de35978af24cfe0167cb8c7dddadeecea5bf4_reversed.mp4"
    },
    {
      "loop": false,
      "auto_next": false,
      "playback_rate": 1.0,
      "reversed_playback_rate": 1.0,
      "notes": "",
      "dedent_notes": true,
      "skip_animations": false,
      "src": null,
      "type": "video",
      "direction": "horizontal",
      "file": "slides\\files\\LeastSq\\41f613476f7ab7276a84b165a92d4555f79add67a263343355139b5ee5c5b73c.mp4",
      "rev_file": "slides\\files\\LeastSq\\41f613476f7ab7276a84b165a92d4555f79add67a263343355139b5ee5c5b73c_reversed.mp4"
    },
    {
      "loop": false,
      "auto_next": false,
      "playback_rate": 1.0,
      "reversed_playback_rate": 1.0,
      "notes": "",
      "dedent_notes": true,
      "skip_animations": false,
      "src": null,
      "type": "video",
      "direction": "horizontal",
      "file": "slides\\files\\LeastSq\\4b3bea4fb40ead6f7abe527f339f22e400fad0b6266b91dad22264acf215fe44.mp4",
      "rev_file": "slides\\files\\LeastSq\\4b3bea4fb40ead6f7abe527f339f22e400fad0b6266b91dad22264acf215fe44_reversed.mp4"
    },
    {
      "loop": false,
      "auto_next": false,
      "playback_rate": 1.0,
      "reversed_playback_rate": 1.0,
      "notes": "",
      "dedent_notes": true,
      "skip_animations": false,
      "src": null,
      "type": "video",
      "direction": "horizontal",
      "file": "slides\\files\\LeastSq\\77e33c71bad68534e4a432a363180260fc54f7ac12b5a92df889ae0a1405d137.mp4",
      "rev_file": "slides\\files\\LeastSq\\77e33c71bad68534e4a432a363180260fc54f7ac12b5a92df889ae0a1405d137_reversed.mp4"
    },
    {
      "loop": false,
      "auto_next": false,
      "playback_rate": 1.0,
      "reversed_playback_rate": 1.0,
      "notes": "",
      "dedent_notes": true,
      "skip_animations": false,
      "src": null,
      "type": "video",
      "direction": "horizontal",
      "file": "slides\\files\\LeastSq\\415172968bd2c5d6d4f5649fd85358f3fc17ab7782f15633b59cef2424748c91.mp4",
      "rev_file": "slides\\files\\LeastSq\\415172968bd2c5d6d4f5649fd85358f3fc17ab7782f15633b59cef2424748c91_reversed.mp4"
    },
    {
      "loop": false,
      "auto_next": false,
      "playback_rate": 1.0,
      "reversed_playback_rate": 1.0,
      "notes": "",
      "dedent_notes": true,
      "skip_animations": false,
      "src": null,
      "type": "video",
      "direction": "horizontal",
      "file": "slides\\files\\LeastSq\\7342d68f0d533676f768baa3acb1f361d1fa3b9c3d6fbe9270ad4f642916bb4a.mp4",
      "rev_file": "slides\\files\\LeastSq\\7342d68f0d533676f768baa3acb1f361d1fa3b9c3d6fbe9270ad4f642916bb4a_reversed.mp4"
    },
    {
      "loop": false,
      "auto_next": false,
      "playback_rate": 1.0,
      "reversed_playback_rate": 1.0,
      "notes": "",
      "dedent_notes": true,
      "skip_animations": false,
      "src": null,
      "type": "video",
      "direction": "horizontal",
      "file": "slides\\files\\LeastSq\\bce71a0bf30446e8bbce8b75791d68aa12b422b1bce414d51ced65069fcd0ccd.mp4",
      "rev_file": "slides\\files\\LeastSq\\bce71a0bf30446e8bbce8b75791d68aa12b422b1bce414d51ced65069fcd0ccd_reversed.mp4"
    },
    {
      "loop": false,
      "auto_next": false,
      "playback_rate": 1.0,
      "reversed_playback_rate": 1.0,
      "notes": "",
      "dedent_notes": true,
      "skip_animations": false,
      "src": null,
      "type": "video",
      "direction": "horizontal",
      "file": "slides\\files\\LeastSq\\47556c050efd6dc33e4bfb5d65bf4b13441332bec3b812e714ccbce1ea7c4319.mp4",
      "rev_file": "slides\\files\\LeastSq\\47556c050efd6dc33e4bfb5d65bf4b13441332bec3b812e714ccbce1ea7c4319_reversed.mp4"
    },
    {
      "loop": false,
      "auto_next": false,
      "playback_rate": 1.0,
      "reversed_playback_rate": 1.0,
      "notes": "",
      "dedent_notes": true,
      "skip_animations": false,
      "src": null,
      "type": "video",
      "direction": "horizontal",
      "file": "slides\\files\\LeastSq\\078ab2cafa4be658d193c2eced64d0fc7f50b70846655f3a24aa031dee6404a3.mp4",
      "rev_file": "slides\\files\\LeastSq\\078ab2cafa4be658d193c2eced64d0fc7f50b70846655f3a24aa031dee6404a3_reversed.mp4"
    },
    {
      "loop": false,
      "auto_next": false,
      "playback_rate": 1.0,
      "reversed_playback_rate": 1.0,
      "notes": "",
      "dedent_notes": true,
      "skip_animations": false,
      "src": null,
      "type": "video",
      "direction": "horizontal",
      "file": "slides\\files\\LeastSq\\d76604f67634c9b81a828765f16ba90fbdc1240167722f3d2b9101887316e86e.mp4",
      "rev_file": "slides\\files\\LeastSq\\d76604f67634c9b81a828765f16ba90fbdc1240167722f3d2b9101887316e86e_reversed.mp4"
    }
  ],
  "resolution": [
    1920,
    1080
  ],
  "background_color": "#04050e"
}